cloe_sql_composer/__init__.py
cloe_sql_composer/cli.py
cloe_sql_composer/config/__init__.py
cloe_sql_composer/config/config.py
cloe_sql_composer/exceptions.py
cloe_sql_composer/loader/__init__.py
cloe_sql_composer/loader/model.py
cloe_sql_composer/metadata/__init__.py
cloe_sql_composer/metadata/base.py
cloe_sql_composer/metadata/mappings.py
cloe_sql_composer/metadata/snowflake.py
cloe_sql_composer/model/__init__.py
cloe_sql_composer/model/base.py
cloe_sql_composer/model/column.py
cloe_sql_composer/model/dtypes.py
cloe_sql_composer/model/models.py
cloe_sql_composer/py.typed
cloe_sql_composer/template/__init__.py
cloe_sql_composer/template/jinja_templates/models/procedure.yaml.j2
cloe_sql_composer/template/jinja_templates/models/table.yaml.j2
cloe_sql_composer/template/jinja_templates/query/metadata.sql.j2
cloe_sql_composer/template/jinja_templates/snowflake/procedure.sql.j2
cloe_sql_composer/template/jinja_templates/snowflake/table.sql.j2
cloe_sql_composer/template/template.py
cloe_sql_composer/writer/__init__.py
cloe_sql_composer/writer/base.py
cloe_sql_composer/writer/model.py
cloe_sql_composer/writer/sql.py
cloe_sql_composer-0.1.0.dist-info/METADATA
cloe_sql_composer-0.1.0.dist-info/WHEEL
cloe_sql_composer-0.1.0.dist-info/entry_points.txt
cloe_sql_composer-0.1.0.dist-info/RECORD
