Metadata-Version: 2.1
Name: cloe-sql-composer
Version: 0.1.0
Summary: Generate DMLs and DDLs using a simplified Metadata model with ymls.
Home-page: https://initions.com/
Author: initions
Author-email: ICSMC_EXT_PYPIORG@accenture.com
License: MIT
Requires-Python: >=3.11,<3.12
Requires-Dist: cloe-util-snowflake-connector (>=1.0.2,<2.0.0)
Requires-Dist: jinja2 (>=3.1.4,<4.0.0)
Requires-Dist: python-dotenv (>=1.0.1,<2.0.0)
Requires-Dist: pyyaml (>=6.0.1,<7.0.0)
Requires-Dist: typer (>=0.12.3,<0.13.0)
